cc_notion/__init__.py
cc_notion/client.py
cc_notion/endpoints.py
cc_notion/errors.py
cc_notion/helpers.py
cc_notion/typing.py
cc_notion-0.1.3.dist-info/METADATA
cc_notion-0.1.3.dist-info/WHEEL
cc_notion-0.1.3.dist-info/top_level.txt
cc_notion-0.1.3.dist-info/RECORD
