Metadata-Version: 2.1
Name: cc-notion
Version: 0.1.3
Summary: my notion package
Home-page: https://github.com/houm01/cc-notion
